probetools/__init__.py
probetools/probetools_v_0_1_9.py
probetools-0.1.9.dist-info/LICENSE
probetools-0.1.9.dist-info/METADATA
probetools-0.1.9.dist-info/WHEEL
probetools-0.1.9.dist-info/entry_points.txt
probetools-0.1.9.dist-info/top_level.txt
probetools-0.1.9.dist-info/RECORD
