Metadata-Version: 2.1
Name: probetools
Version: 0.1.9
Summary: Hybridization probe design for targeted genomic sequencing of diverse and hypervariable viral taxa
Home-page: https://github.com/kevinkuchinski/probetools
Author: Kevin Kuchinski
Author-email: kevin.kuchinski@bccdc.ca
License: UNKNOWN
Project-URL: Bug Tracker, https://github.com/kevinkuchinski/probetools/issues
Platform: UNKNOWN
Classifier: Programming Language :: Python :: 3
Classifier: License :: OSI Approved :: MIT License
Classifier: Operating System :: OS Independent
Requires-Python: >=3.7
License-File: LICENSE
